pc_zap_scrapper/__init__.py
pc_zap_scrapper/__main__.py
pc_zap_scrapper/_version.py
pc_zap_scrapper/imoveis_db.py
pc_zap_scrapper/load.py
pc_zap_scrapper/maps.py
pc_zap_scrapper/scrap.py
pc_zap_scrapper/transform.py
pc_zap_scrapper/utils.py
pc_zap_scrapper/datasets/external/neighbor_latlong.parquet
pc_zap_scrapper-1.0.2.dist-info/LICENSE
pc_zap_scrapper-1.0.2.dist-info/METADATA
pc_zap_scrapper-1.0.2.dist-info/WHEEL
pc_zap_scrapper-1.0.2.dist-info/entry_points.txt
pc_zap_scrapper-1.0.2.dist-info/top_level.txt
pc_zap_scrapper-1.0.2.dist-info/RECORD
