Metadata-Version: 2.1
Name: pc-zap-scrapper
Version: 1.0.2
Summary: Um template para começar o desenvolvimento de apps
Author-email: Eduardo <emdemor415@gmail.com.br>
License: Copyright (c) 2023, Eduardo Morais
Keywords: template,app
Classifier: Environment :: Console
Classifier: License :: OSI Approved :: MIT License
Classifier: Natural Language :: Portuguese (Brazilian)
Classifier: Operating System :: OS Independent
Classifier: Programming Language :: Python :: 3
Classifier: Programming Language :: Python :: 3.10
Classifier: Topic :: Utilities
Requires-Python: >=3.9
License-File: LICENSE
Requires-Dist: bump2version (==1.0.1)
Requires-Dist: click (==8.1.3)
Requires-Dist: click-default-group (==1.2.2)
Requires-Dist: sphinx (==6.1.1)
Requires-Dist: sphinx-rtd-theme (==0.5.1)
Requires-Dist: toml (==0.10.2)
Requires-Dist: fastparquet (==0.8.1)
Requires-Dist: geopy (==2.2.0)
Requires-Dist: pandas (==1.2.4)
Requires-Dist: pandasql (==0.7.3)
Requires-Dist: pyarrow
Requires-Dist: psycopg2-binary (==2.9.5)
Requires-Dist: python-dotenv (==0.20.0)
Requires-Dist: sqlalchemy (==1.3.20)
Requires-Dist: zapscrapper (==0.0.7)
Requires-Dist: loguru (==0.6.0)
